ann_test.cpp
kdtree.h.not_ready_for_prime_time
license.txt
setup.cfg
setup.py
site.cfg
swig_ann.tmproj
./scikits/__init__.py
scikits/__init__.py
scikits.ann.egg-info/PKG-INFO
scikits.ann.egg-info/SOURCES.txt
scikits.ann.egg-info/dependency_links.txt
scikits.ann.egg-info/namespace_packages.txt
scikits.ann.egg-info/native_libs.txt
scikits.ann.egg-info/requires.txt
scikits.ann.egg-info/top_level.txt
scikits/ann/ANN.i
scikits/ann/__init__.py
scikits/ann/info.py
scikits/ann/kdtree.h
scikits/ann/numpy.i
scikits/ann/setup.py
scikits/ann/version.py
scikits/ann/tests/test_ann.py
