Metadata-Version: 1.0
Name: scikits.ann
Version: 0.2.dev-r800
Summary: Approximate Nearest Neighbor library wrapper for Numpy
Home-page: UNKNOWN
Author: Barry Wark
Author-email: barrywark@gmail.com
License: GNU LGPL
Platform: UNKNOWN
Classifier: Development Status :: 4 - Beta
Classifier: Intended Audience :: Developers
Classifier: Intended Audience :: Science/Research
Classifier: License :: OSI Approved :: GNU Library or Lesser General Public License (LGPL)
Classifier: Programming Language :: Python
Classifier: Topic :: Scientific/Engineering
Classifier: Topic :: Software Development :: Libraries :: Python Modules
